pymaven/__init__.py
pymaven/artifact.py
pymaven/client.py
pymaven/constants.py
pymaven/errors.py
pymaven/pom.py
pymaven/utils.py
pymaven/versioning.py
python_maven-0.0.3.dist-info/LICENSE
python_maven-0.0.3.dist-info/METADATA
python_maven-0.0.3.dist-info/WHEEL
python_maven-0.0.3.dist-info/top_level.txt
python_maven-0.0.3.dist-info/RECORD
