Metadata-Version: 2.1
Name: python-maven
Version: 0.0.3
Summary: Pymaven is a Python library for interfacing with the maven build system.
Home-page: https://github.com/sassoftware/pymaven
Author: Walter Scheper
Author-email: Walter.Scheper@sas.com
License: MIT
Keywords: maven
Classifier: Development Status :: 5 - Production/Stable
Classifier: Environment :: Plugins
Classifier: Intended Audience :: Developers
Classifier: License :: OSI Approved :: MIT License
Classifier: Operating System :: OS Independent
Classifier: Programming Language :: Python :: 2.7
Classifier: Programming Language :: Python :: 3.3
Classifier: Programming Language :: Python :: 3.4
Classifier: Programming Language :: Python :: 3.5
Classifier: Programming Language :: Python :: 3.6
Classifier: Programming Language :: Python :: 3.7
Classifier: Programming Language :: Python :: 3.8
Classifier: Topic :: Software Development
License-File: LICENSE
